binarypipe/__init__.py
binarypipe/__main__.py
binarypipe/imagepipe.py
binarypipe-0.1.1.dist-info/LICENSE
binarypipe-0.1.1.dist-info/METADATA
binarypipe-0.1.1.dist-info/WHEEL
binarypipe-0.1.1.dist-info/top_level.txt
binarypipe-0.1.1.dist-info/RECORD
